<annotation>
	<folder>dosa</folder>
	<filename>aug_125_Copy.jpg</filename>
	<path>D:\tf_obj_dataset\dosa\aug_125_Copy.jpg</path>
	<source>
		<database>Unknown</database>
	</source>
	<size>
		<width>1212</width>
		<height>900</height>
		<depth>3</depth>
	</size>
	<segmented>0</segmented>
	<object>
		<name>dosa</name>
		<pose>Unspecified</pose>
		<truncated>0</truncated>
		<difficult>0</difficult>
		<bndbox>
			<xmin>54</xmin>
			<ymin>207</ymin>
			<xmax>1017</xmax>
			<ymax>507</ymax>
		</bndbox>
	</object>
</annotation>
