<annotation>
	<folder>donuts</folder>
	<filename>105814.jpg</filename>
	<path>D:\tf_obj_dataset\donuts\105814.jpg</path>
	<source>
		<database>Unknown</database>
	</source>
	<size>
		<width>384</width>
		<height>512</height>
		<depth>3</depth>
	</size>
	<segmented>0</segmented>
	<object>
		<name>donuts</name>
		<pose>Unspecified</pose>
		<truncated>0</truncated>
		<difficult>0</difficult>
		<bndbox>
			<xmin>161</xmin>
			<ymin>177</ymin>
			<xmax>313</xmax>
			<ymax>305</ymax>
		</bndbox>
	</object>
	<object>
		<name>donuts</name>
		<pose>Unspecified</pose>
		<truncated>0</truncated>
		<difficult>0</difficult>
		<bndbox>
			<xmin>78</xmin>
			<ymin>122</ymin>
			<xmax>211</xmax>
			<ymax>221</ymax>
		</bndbox>
	</object>
</annotation>
